bsport_access_control_client/__init__.py
bsport_access_control_client/api_client.py
bsport_access_control_client/api_response.py
bsport_access_control_client/configuration.py
bsport_access_control_client/exceptions.py
bsport_access_control_client/py.typed
bsport_access_control_client/rest.py
bsport_access_control_client/api/__init__.py
bsport_access_control_client/api/auth_api.py
bsport_access_control_client/api/place_api.py
bsport_access_control_client/api/place_restriction_api.py
bsport_access_control_client/api/provider_api.py
bsport_access_control_client/api/visitor_access_right_api.py
bsport_access_control_client/api/visitor_api.py
bsport_access_control_client/api/visitor_restriction_api.py
bsport_access_control_client/api/webhooks_api.py
bsport_access_control_client/models/__init__.py
bsport_access_control_client/models/kisi_place.py
bsport_access_control_client/models/kisi_visitor.py
bsport_access_control_client/models/paginated_place_list.py
bsport_access_control_client/models/paginated_place_restriction_list.py
bsport_access_control_client/models/paginated_provider_config_list.py
bsport_access_control_client/models/paginated_visitor_access_right_list.py
bsport_access_control_client/models/paginated_visitor_list.py
bsport_access_control_client/models/paginated_visitor_restriction_list.py
bsport_access_control_client/models/patched_place.py
bsport_access_control_client/models/patched_place_restriction.py
bsport_access_control_client/models/patched_provider_config.py
bsport_access_control_client/models/patched_visitor.py
bsport_access_control_client/models/patched_visitor_access_right.py
bsport_access_control_client/models/patched_visitor_restriction.py
bsport_access_control_client/models/place.py
bsport_access_control_client/models/place_restriction.py
bsport_access_control_client/models/provider_config.py
bsport_access_control_client/models/provider_type_enum.py
bsport_access_control_client/models/token_obtain_pair.py
bsport_access_control_client-1.0.0.dist-info/METADATA
bsport_access_control_client-1.0.0.dist-info/WHEEL
bsport_access_control_client-1.0.0.dist-info/top_level.txt
bsport_access_control_client-1.0.0.dist-info/RECORD
